Workbook
Name aporte_inicial: Planilha1!$D$22
Name aporte_mensal: Planilha1!$D$23
Name patrimonio: Planilha1!$D$26
Name qtd_anos: Planilha1!$D$24
Name rendiemnto_mensal: Planilha1!$D$25
Name rendimento_carteira: Planilha1!$D$18
Name rendimento_mensal: Planilha1!$D$25
Name salario: Planilha1!$D$17

Sheet Planilha1
B16: CINFIGURAÇÕES
B17: Salário | D17: 5000
B18: Rendimenta da Carteira | D18: 0.01
B19: Sugestão de Investimento (30%) | D19: =salario*30% -> 1500
B21: INVESTIEMNTO MENSAL
B22: Aporte Inicial? | D22: 5000
B23: Quanto investir por mês ? | D23: 1500
B24: Por Quantos Anos ? | D24: 5
B25: Taxa de Rendimento mensal ? | D25: =rendimento_carteira -> 0.01
B26: Patrimônio acumulado ? | D26: =FV(rendiemnto_mensal,qtd_anos*12,aporte_mensal*-1,aporte_inicial) -> 113421.02
B27: Dividendos Mensais ? | D27: =patrimonio*rendiemnto_mensal -> 1134.2102
B29: Cenários | D29: Dividendo
A30: 2 | B30: Quanto em 2 Anos? | C30: =FV(rendiemnto_mensal,$A30*12,aporte_mensal*-1,aporte_inicial) -> 34111.524 | D30: =C30*rendiemnto_mensal -> 341.11524
A31: 5 | B31: Quanto em 5 Anos? | C31: =FV(rendiemnto_mensal,$A31*12,aporte_mensal*-1,aporte_inicial) -> 113421.02 | D31: =C31*rendiemnto_mensal -> 1134.2102
A32: 10 | B32: Quanto em 10 Anos? | C32: =FV(rendiemnto_mensal,$A32*12,aporte_mensal*-1,aporte_inicial) -> 328556.1 | D32: =C32*rendiemnto_mensal -> 3285.561
A33: 20 | B33: Quanto em 20 Anos? | C33: =FV(rendiemnto_mensal,$A33*12,aporte_mensal*-1,aporte_inicial) -> 1429420.3 | D33: =C33*rendiemnto_mensal -> 14294.203
A34: 30 | B34: Quanto em 30 Anos? | C34: =FV(rendiemnto_mensal,$A34*12,aporte_mensal*-1,aporte_inicial) -> 5062698 | D34: =C34*rendiemnto_mensal -> 50626.98
B37: PERFIL | C37: Moderado
B38: VALOR INVESTIDO POR MÊS | C38: =aporte_mensal -> 1500
B40: TIPO DE FII | C40: Percentual Sugerido | D40: Valores
B41: PAPEL | C41: =VLOOKUP($C$37 &"-"& B41,Planilha2!$A:$D,4,FALSE) -> 0.32 | D41: =C41*$C$38 -> 480
B42: TIJOLO | C42: =VLOOKUP($C$37 &"-"& B42,Planilha2!$A:$D,4,FALSE) -> 0.35 | D42: =C42*$C$38 -> 525
B43: HÍBRIDOS | C43: =VLOOKUP($C$37 &"-"& B43,Planilha2!$A:$D,4,FALSE) -> 0.08 | D43: =C43*$C$38 -> 120
B44: FOFs | C44: =VLOOKUP($C$37 &"-"& B44,Planilha2!$A:$D,4,FALSE) -> 0.05 | D44: =C44*$C$38 -> 75
B45: DESENVOLVIMENTO | C45: =VLOOKUP($C$37 &"-"& B45,Planilha2!$A:$D,4,FALSE) -> 0.1 | D45: =C45*$C$38 -> 150
B46: HOTELARIAS | C46: =VLOOKUP($C$37 &"-"& B46,Planilha2!$A:$D,4,FALSE) -> 0.1 | D46: =C46*$C$38 -> 150

Sheet Planilha2
A2: CHAVE | B2: PERFIL | C2: TIPO DE FII | D2: %
A3: =B3&"-"&C3 -> Conservador-PAPEL | B3: Conservador | C3: PAPEL | D3: 0.3
A4: =B4&"-"&C4 -> Conservador-TIJOLO | B4: Conservador | C4: TIJOLO | D4: 0.5
A5: =B5&"-"&C5 -> Conservador-HÍBRIDOS | B5: Conservador | C5: HÍBRIDOS | D5: 0.1
A6: =B6&"-"&C6 -> Conservador-FOFs | B6: Conservador | C6: FOFs | D6: 0.1
A7: =B7&"-"&C7 -> Conservador-DESENVOLVIMENTO | B7: Conservador | C7: DESENVOLVIMENTO | D7: 0
A8: =B8&"-"&C8 -> Conservador-HOTELARIAS | B8: Conservador | C8: HOTELARIAS | D8: 0
A9: =B9&"-"&C9 -> Moderado-PAPEL | B9: Moderado | C9: PAPEL | D9: 0.32
A10: =B10&"-"&C10 -> Moderado-TIJOLO | B10: Moderado | C10: TIJOLO | D10: 0.35
A11: =B11&"-"&C11 -> Moderado-HÍBRIDOS | B11: Moderado | C11: HÍBRIDOS | D11: 0.08
A12: =B12&"-"&C12 -> Moderado-FOFs | B12: Moderado | C12: FOFs | D12: 0.05
A13: =B13&"-"&C13 -> Moderado-DESENVOLVIMENTO | B13: Moderado | C13: DESENVOLVIMENTO | D13: 0.1
A14: =B14&"-"&C14 -> Moderado-HOTELARIAS | B14: Moderado | C14: HOTELARIAS | D14: 0.1
... A20: =B20&"-"&C20 -> Agressivo-HOTELARIAS | B20: Agressivo | C20: HOTELARIAS | D20: 0.1
